<?xml version="1.0" encoding="UTF-8"?>

<!-- generated on 2025-04-25 01:40:47 by Eclipse SUMO sumo Version 1.20.0
<configuration xmlns:xsi="http://www.w3.org/2001/XMLSchema-instance" xsi:noNamespaceSchemaLocation="http://sumo.dlr.de/xsd/sumoConfiguration.xsd">

    <input>
        <net-file value="../networks/saint_arnoult/saint_arnoult.net.xml"/>
        <additional-files value="../results/sai_iql_1/det.add.xml,../results/sai_iql_1/route.rou.xml"/>
    </input>

    <output>
        <tripinfo-output value="../results/sai_iql_1/SUMO_output/detailed_sumo_stats_3002.xml"/>
        <statistic-output value="../results/sai_iql_1/SUMO_output/sumo_stats_3002.xml"/>
    </output>

    <processing>
        <time-to-teleport value="-1"/>
    </processing>

    <report>
        <no-step-log value="true"/>
    </report>

    <random_number>
        <seed value="42"/>
    </random_number>

</configuration>
-->

<statistics xmlns:xsi="http://www.w3.org/2001/XMLSchema-instance" xsi:noNamespaceSchemaLocation="http://sumo.dlr.de/xsd/statistic_file.xsd">
    <performance clockBegin="1745538047.55" clockEnd="1745538049.42" clockDuration="1.87" traciDuration="1.70" realTimeFactor="1124.33" vehicleUpdatesPerSecond="24239.01" personUpdatesPerSecond="0.00" begin="0.00" end="2098.00" duration="2098.00"/>
    <vehicles loaded="222" inserted="222" running="0" waiting="0"/>
    <teleports total="0" jam="0" yield="0" wrongLane="0"/>
    <safety collisions="0" emergencyStops="0" emergencyBraking="0"/>
    <persons loaded="0" running="0" jammed="0"/>
    <personTeleports total="0" abortWait="0" wrongDest="0"/>
    <vehicleTripStatistics count="222" routeLength="1639.37" speed="8.23" duration="203.74" waitingTime="0.41" timeLoss="26.30" departDelay="0.04" departDelayWaiting="-1.00" totalTravelTime="45230.00" totalDepartDelay="8.00"/>
    <pedestrianStatistics number="0" routeLength="0.00" duration="0.00" timeLoss="0.00"/>
    <rideStatistics number="0"/>
    <transportStatistics number="0"/>
</statistics>
